README.md
setup.py
sx/__init__.py
sx/__main__.py
sx/utils.py
sx.egg-info/PKG-INFO
sx.egg-info/SOURCES.txt
sx.egg-info/dependency_links.txt
sx.egg-info/entry_points.txt
sx.egg-info/not-zip-safe
sx.egg-info/requires.txt
sx.egg-info/top_level.txt
sx/actions/script.py
sx/actions/boot/__init__.py
sx/actions/boot/actions.py
sx/actions/create/__init__.py
sx/actions/export/__init__.py
sx/actions/export/systemd.py
sx/helpers/__init__.py
sx/helpers/decorators.py
sx/helpers/service.py
sx/helpers/util.py
sx/stubs/environment.py
sx/stubs/process_log.py
sx/stubs/settings.py