Metadata-Version: 2.1
Name: sx
Version: 0.6.0
Summary: Framework to manage gRPC-based microservices application
Home-page: https://github.com/itsmealves/sx
Author: Gabriel Alves
Author-email: gabriel.alves@pickcells.bio
License: MIT
Download-URL: https://github.com/itsmealves/sx/releases/download/0.6.0/sx-0.6.0.tar.gz
Keywords: sx microservices rpc grpc Framework
Platform: UNKNOWN
Requires-Python: >=3.5
